kestrel_llm/__init__.py
kestrel_llm/cli.py
kestrel_llm/logging_utils.py
kestrel_llm/repo_utils.py
kestrel_llm/update_llm_symbols.py
kestrel_llm/verify_llm_docs.py
kestrel_llm-0.1.3.dist-info/licenses/LICENSE
kestrel_llm-0.1.3.dist-info/METADATA
kestrel_llm-0.1.3.dist-info/WHEEL
kestrel_llm-0.1.3.dist-info/entry_points.txt
kestrel_llm-0.1.3.dist-info/top_level.txt
kestrel_llm-0.1.3.dist-info/RECORD
