Metadata-Version: 2.4
Name: kestrel-llm
Version: 0.1.3
Summary: Utilities to verify and maintain LLM.txt files (coverage, sorting, symbols blocks).
Author: kestrel-llm contributors
License: MIT
Classifier: Intended Audience :: Developers
Classifier: License :: OSI Approved :: MIT License
Classifier: Programming Language :: Python :: 3
Classifier: Topic :: Software Development :: Documentation
Classifier: Topic :: Software Development :: Quality Assurance
Requires-Python: >=3.10
License-File: LICENSE
Provides-Extra: dev
Requires-Dist: ty>=0.0.2; extra == "dev"
Requires-Dist: pytest>=8; extra == "dev"
Requires-Dist: ruff>=0.5; extra == "dev"
Dynamic: license-file
